bigword/__init__.py
bigword/__main__.py
bigword/grid.py
bigword/letter_class.py
bigword/letter_dict.py
bigword-0.1.0.dist-info/METADATA
bigword-0.1.0.dist-info/WHEEL
bigword-0.1.0.dist-info/entry_points.txt
bigword-0.1.0.dist-info/top_level.txt
bigword-0.1.0.dist-info/RECORD
