Metadata-Version: 2.1
Name: bigword
Version: 0.1.0
Summary: Print big words on a grid
Home-page: https://github.com/caseyrwebb/bigword
Author: Casey Webb
License: UNKNOWN
Platform: UNKNOWN
Requires-Python: >=3.10.5
